word_to_markdown_mcp/__init__.py
word_to_markdown_mcp/server.py
word_to_markdown_mcp-0.1.0.dist-info/METADATA
word_to_markdown_mcp-0.1.0.dist-info/WHEEL
word_to_markdown_mcp-0.1.0.dist-info/entry_points.txt
word_to_markdown_mcp-0.1.0.dist-info/RECORD
